pysdic/__init__.py
pysdic/__main__.py
pysdic/__version__.py
pysdic/blender/__init__.py
pysdic/blender/blender_camera.py
pysdic/blender/blender_experiment.py
pysdic/blender/blender_material_bsdf.py
pysdic/blender/blender_mesh.py
pysdic/blender/blender_spotlight.py
pysdic/blender/default_materials.py
pysdic/core/BRDF_models.py
pysdic/core/create_3D_surface_meshes.py
pysdic/core/gauss_points.py
pysdic/core/integration_points_operations.py
pysdic/core/photometric_operations.py
pysdic/core/shape_functions.py
pysdic/core/temporal_derivation.py
pysdic/core/triangle_3_mesh_operations.py
pysdic/core/objects/camera.py
pysdic/core/objects/image.py
pysdic/core/objects/image_projection_result.py
pysdic/core/objects/integration_points.py
pysdic/core/objects/mesh.py
pysdic/core/objects/point_cloud.py
pysdic/core/objects/projection_result.py
pysdic/core/objects/view.py
pysdic/sdic/__init__.py
pysdic/sdic/build_displacement_operator.py
pysdic-1.1.4.dist-info/licenses/LICENSE
pysdic-1.1.4.dist-info/METADATA
pysdic-1.1.4.dist-info/WHEEL
pysdic-1.1.4.dist-info/top_level.txt
pysdic-1.1.4.dist-info/RECORD
