Metadata-Version: 2.4
Name: pysdic
Version: 1.1.4
Summary: Python Stereo Digital Image Correlation Toolbox.
Author-email: Artezaru <artezaru.github@proton.me>
License: Copyright 2025 Artezaru
Project-URL: Homepage, https://github.com/Artezaru/pysdic
Project-URL: Documentation, https://Artezaru.github.io/pysdic
Project-URL: Source, https://github.com/Artezaru/pysdic
Project-URL: Tracker, https://github.com/Artezaru/pysdic/issues
Classifier: Programming Language :: Python :: 3
Classifier: License :: OSI Approved :: Apache Software License
Classifier: Operating System :: OS Independent
Requires-Python: >=3.10
License-File: LICENSE
Requires-Dist: numpy>=1.24.0
Requires-Dist: py3dframe>=0.2.5
Requires-Dist: meshio>=5.3.0
Requires-Dist: pyvista>=0.46.3
Requires-Dist: scipy>=1.10.0
Requires-Dist: opencv-python-headless>=4.12.0
Requires-Dist: open3d>=0.19.0
Requires-Dist: matplotlib>=3.7.0
Requires-Dist: pycvcam>=1.5.0
Provides-Extra: dev
Requires-Dist: sphinx; extra == "dev"
Requires-Dist: pydata-sphinx-theme; extra == "dev"
Requires-Dist: numpydoc; extra == "dev"
Requires-Dist: pytest; extra == "dev"
Requires-Dist: pytest-cov; extra == "dev"
Requires-Dist: bumpver; extra == "dev"
Requires-Dist: twine; extra == "dev"
Requires-Dist: wheel; extra == "dev"
Requires-Dist: build; extra == "dev"
Requires-Dist: setuptools; extra == "dev"
Requires-Dist: setuptools-scm; extra == "dev"
Dynamic: license-file
